llama/__init__.py
llama/app.py
llama/config.py
llama/metrics.py
llama/scraper.py
llama/collector.py
llama/ping.py
llama/udp.py
llama/util.py
llama/version.py
llama/tests/__init__.py
llama/tests/metrics_test.py
llama/tests/ping_test.py
llama/tests/util_test.py
llama/tests/udp_test.py
llama/templates/index.html
llama-0.1.1.data/scripts/llama_collector
llama-0.1.1.dist-info/top_level.txt
llama-0.1.1.dist-info/METADATA
llama-0.1.1.dist-info/DESCRIPTION.rst
llama-0.1.1.dist-info/metadata.json
llama-0.1.1.dist-info/WHEEL
llama-0.1.1.dist-info/RECORD
