Metadata-Version: 2.0
Name: llama
Version: 0.1.1
Summary: LLAMA - Loss & LAtency MAtrix
Home-page: https://github.com/dropbox/llama
Author: Daniel Martin
Author-email: dmar@dropbox.com
License: Apache
Keywords: llama udp loss latency matrix probe packet
Platform: UNKNOWN
Classifier: Development Status :: 1 - Planning
Classifier: Intended Audience :: System Administrators
Classifier: License :: OSI Approved :: Apache Software License
Classifier: Operating System :: POSIX :: Linux
Classifier: Programming Language :: Python :: 2.7
Classifier: Topic :: System :: Networking :: Monitoring
Requires-Dist: apscheduler (>=3.2.0)
Requires-Dist: docopt (>=0.6.2)
Requires-Dist: flask (>=0.10.1)
Requires-Dist: futures (>=3.0.3)
Requires-Dist: humanfriendly (>=1.44.3)
Requires-Dist: influxdb (>=2.12.0)
Requires-Dist: pyyaml (>=3.11)
Requires-Dist: ipaddress (>=1.0.14)
